{
  "source_file": "LBL 3:16:22.pdf",
  "production_info": {
    "production_name": null,
    "date": "March 16, 2022",
    "production_company": null,
    "day_info": "Day 3 OF 24"
  },
  "crew": [],
  "talent": [
    {
      "character": null,
      "talent_name": "Michelle N. Carter",
      "call_time": "9:00AM"
    },
    {
      "character": null,
      "talent_name": "Byron Marc Newsome",
      "call_time": "8:45AM"
    },
    {
      "character": null,
      "talent_name": "Shirley Jordan",
      "call_time": "8:45AM"
    },
    {
      "character": null,
      "talent_name": "Kiana Nicole Washington",
      "call_time": "10:00A"
    },
    {
      "character": null,
      "talent_name": "Gordan James Jr.",
      "call_time": "10:00A"
    },
    {
      "character": null,
      "talent_name": "TOTAL CAST:5",
      "call_time": null
    },
    {
      "character": null,
      "talent_name": "STAND-INS / EXTRAS",
      "call_time": null
    },
    {
      "character": null,
      "talent_name": "Amt.",
      "call_time": null
    },
    {
      "character": null,
      "talent_name": "TOTAL BG: 0",
      "call_time": null
    },
    {
      "character": null,
      "talent_name": "ADVANCE SCHEDULE:",
      "call_time": null
    },
    {
      "character": null,
      "talent_name": "SCENE #",
      "call_time": null
    },
    {
      "character": null,
      "talent_name": "INT - MORRIS FAMILY HOME - KITCHEN EVENING N10\nEric and Tracy are talking while they work in the kitchen.",
      "call_time": null
    },
    {
      "character": null,
      "talent_name": "Shadow Hills, CA 91040",
      "call_time": null
    },
    {
      "character": null,
      "talent_name": "INT - MORRIS FAMILY HOME - BEVERLY & ERIC’S EVENING N6\nWe go back and forth between Beverly’s side of the conversation and Eric’s.",
      "call_time": null
    },
    {
      "character": null,
      "talent_name": "TOTAL PAGES: 7 2/8",
      "call_time": null
    },
    {
      "character": null,
      "talent_name": "ADVANCE SCHEDULE: D",
      "call_time": null
    },
    {
      "character": null,
      "talent_name": "SCENE #",
      "call_time": null
    },
    {
      "character": null,
      "talent_name": "INT - MORRIS FAMILY HOME - KITCHEN NIGHT N13\nBeverly arrives home and finds Tracy in the kitchen.",
      "call_time": null
    },
    {
      "character": null,
      "talent_name": "Shadow Hills, CA 91040",
      "call_time": null
    },
    {
      "character": null,
      "talent_name": "INT - MORRIS FAMILY HOME - KITCHEN DAY D14\nWe go back and forth between Beverly and Dr. Secada.",
      "call_time": null
    },
    {
      "character": null,
      "talent_name": "INT - MORRIS FAMILY HOME - KITCHEN/OUTSIDE NIGHT N3\nBeverly is in her kitchen, cleaning up. She hums. Ernestine enters",
      "call_time": null
    },
    {
      "character": null,
      "talent_name": "TOTAL PAGES:",
      "call_time": null
    },
    {
      "character": null,
      "talent_name": "UPM: Laura Buckles",
      "call_time": null
    },
    {
      "character": null,
      "talent_name": "FUN FACT: There is nothing more terrifying then stumbling onto an old rusty school bus packed full of clowns who came from outer space.",
      "call_time": null
    }
  ]
}