{
  "source_file": "Peezy 1:16:22.pdf",
  "production_info": {
    "production_name": null,
    "date": "JANUARY 16th, 2022",
    "production_company": "Peezy WHIPALO LLC WHIPALO LLC",
    "day_info": null
  },
  "crew": [],
  "talent": [
    {
      "character": null,
      "talent_name": "Prep time",
      "call_time": null
    },
    {
      "character": null,
      "talent_name": "The house",
      "call_time": null
    },
    {
      "character": null,
      "talent_name": "B Roll/ exterior/ interior",
      "call_time": null
    },
    {
      "character": null,
      "talent_name": "Ice Cream Truck",
      "call_time": null
    },
    {
      "character": null,
      "talent_name": "Ice Cream Truck (2)",
      "call_time": null
    },
    {
      "character": null,
      "talent_name": "Pack up",
      "call_time": null
    },
    {
      "character": null,
      "talent_name": "Total Pages:",
      "call_time": null
    },
    {
      "character": null,
      "talent_name": "PEEZY",
      "call_time": "12:30pm"
    }
  ]
}